suffixtree/__init__.py
suffixtree/release.py
suffixtree/suffixtree.py
suffixtree/tree.py
suffixtree-0.2.0.dist-info/LICENSE
suffixtree-0.2.0.dist-info/METADATA
suffixtree-0.2.0.dist-info/WHEEL
suffixtree-0.2.0.dist-info/entry_points.txt
suffixtree-0.2.0.dist-info/top_level.txt
suffixtree-0.2.0.dist-info/RECORD
