Metadata-Version: 2.1
Name: suffixtree
Version: 0.2.0
Summary: Yet another suffix tree implementation in Python
Home-page: https://github.com/cartoonist/suffixtree
Author: Ali Ghaffaari
Author-email: ali.ghaffaari@mpi-inf.mpg.de
License: MIT
Download-URL: https://github.com/cartoonist/suffixtree/tarball/0.2.0
Keywords: suffix tree indexing data-structure
Platform: UNKNOWN
Classifier: Development Status :: 3 - Alpha
Classifier: License :: OSI Approved :: MIT License
Classifier: Programming Language :: Python :: 3
Classifier: Programming Language :: Python :: 3.5
Classifier: Programming Language :: Python :: 3.6
Classifier: Programming Language :: Python :: 3.7
Classifier: Programming Language :: Python :: 3.8
Classifier: Intended Audience :: Science/Research
Classifier: Topic :: Text Processing :: Indexing
Requires-Dist: graphviz (==0.4.10)
Provides-Extra: test
Requires-Dist: nose (>=1.0) ; extra == 'test'
Requires-Dist: coverage ; extra == 'test'
